{
  "abiValidationFailures": [],
  "generatedAt": "1970-01-01T00:00:00.000Z",
  "generatorVersion": "2",
  "ignoredNonAdminAssignments": 14,
  "overloadNames": {
    "cohortRegistry": [
      "getCohortWeight"
    ],
    "commerceDisputes": [],
    "credentialManager": [],
    "engagements": [],
    "housingManager": [
      "totalSupply"
    ],
    "investmentCohortManager": [],
    "marketplace": [],
    "positionManager": [],
    "revenueRouter": [],
    "treasuryAdapter": [],
    "valuableActionRegistry": [],
    "verifierElection": [],
    "verifierPowerToken": []
  },
  "profileHash": "3daf023ed729ac3ebd43326b8b2ae0f0e8402c25a2decb9f3b656929936548f4",
  "profileId": "base-sepolia-v1",
  "signatureCount": 47,
  "skippedTargets": [],
  "targetCount": 13
}
